LICENSE
MANIFEST.in
README.txt
setup.py
crawlermaster/__init__.py
crawlermaster/cmparser.py
crawlermaster/cmselector.py
crawlermaster/cmspider.py
crawlermaster/launcher.py
crawlermaster/utility.py
crawlermaster.egg-info/PKG-INFO
crawlermaster.egg-info/SOURCES.txt
crawlermaster.egg-info/dependency_links.txt
crawlermaster.egg-info/entry_points.txt
crawlermaster.egg-info/requires.txt
crawlermaster.egg-info/top_level.txt
crawlermaster/mod/__init__.py
crawlermaster/resource/__init__.py
crawlermaster/resource/chromedriver.exe
crawlermaster/resource/techcrunch_news_csslist.json
crawlermaster/ui/__init__.py